{
  "version": "7",
  "dialect": "postgresql",
  "entries": [
    {
      "idx": 0,
      "version": "7",
      "when": 1757146533099,
      "tag": "0000_handy_carnage",
      "breakpoints": true
    },
    {
      "idx": 1,
      "version": "7",
      "when": 1757206390355,
      "tag": "0001_milky_hardball",
      "breakpoints": true
    },
    {
      "idx": 2,
      "version": "7",
      "when": 1757623148944,
      "tag": "0002_brave_charles_xavier",
      "breakpoints": true
    },
    {
      "idx": 3,
      "version": "7",
      "when": 1757624172624,
      "tag": "0003_solid_maginty",
      "breakpoints": true
    },
    {
      "idx": 4,
      "version": "7",
      "when": 1757659585945,
      "tag": "0004_peaceful_sauron",
      "breakpoints": true
    },
    {
      "idx": 5,
      "version": "7",
      "when": 1757660066346,
      "tag": "0005_right_the_initiative",
      "breakpoints": true
    },
    {
      "idx": 6,
      "version": "7",
      "when": 1757661731475,
      "tag": "0006_flimsy_micromacro",
      "breakpoints": true
    },
    {
      "idx": 7,
      "version": "7",
      "when": 1757870177255,
      "tag": "0007_romantic_mephisto",
      "breakpoints": true
    },
    {
      "idx": 8,
      "version": "7",
      "when": 1757945945511,
      "tag": "0008_tan_mister_fear",
      "breakpoints": true
    },
    {
      "idx": 9,
      "version": "7",
      "when": 1757946197015,
      "tag": "0009_shiny_silver_fox",
      "breakpoints": true
    }
  ]
}